hecdss/__init__.py
hecdss/array_container.py
hecdss/catalog.py
hecdss/cwms_utility.py
hecdss/dateconverter.py
hecdss/download_hecdss.py
hecdss/dss_type.py
hecdss/dsspath.py
hecdss/gridded_data.py
hecdss/hec_dss_native-readme.md
hecdss/hecdss.py
hecdss/irregular_timeseries.py
hecdss/location_info.py
hecdss/native.py
hecdss/paired_data.py
hecdss/record_type.py
hecdss/regular_timeseries.py
hecdss/text.py
hecdss/lib/.gitkeep
hecdss/lib/hecdss.dll
hecdss/lib/libhecdss.so
hecdss-0.1.29.dist-info/licenses/LICENSE.md
hecdss-0.1.29.dist-info/METADATA
hecdss-0.1.29.dist-info/WHEEL
hecdss-0.1.29.dist-info/top_level.txt
hecdss-0.1.29.dist-info/RECORD
