Metadata-Version: 2.4
Name: hecdss
Version: 0.1.29
Summary: Python wrapper for the HEC-DSS file database C library.
Home-page: https://github.com/HydrologicEngineeringCenter/hec-dss-python
Author: Hydrologic Engineering Center
Author-email: hec.dss@usace.army.mil
Classifier: Programming Language :: Python :: 3
Classifier: License :: OSI Approved :: MIT License
Classifier: Operating System :: OS Independent
Requires-Python: >=3.8
License-File: LICENSE.md
Requires-Dist: numpy
Requires-Dist: tzdata
Dynamic: license-file
